findspark.py
findspark-2.0.0.dist-info/LICENSE.md
findspark-2.0.0.dist-info/METADATA
findspark-2.0.0.dist-info/WHEEL
findspark-2.0.0.dist-info/top_level.txt
findspark-2.0.0.dist-info/RECORD
