Metadata-Version: 2.1
Name: findspark
Version: 2.0.0
Summary: Find pyspark to make it importable.
Home-page: https://github.com/minrk/findspark
Author: Min RK
Author-email: benjaminrk@gmail.com
License: BSD (3-clause)
Platform: UNKNOWN
License-File: LICENSE.md
